cubicweb_inlinedit/__init__.py
cubicweb_inlinedit/__pkginfo__.py
cubicweb_inlinedit/data/cubes.inlinedit.js
cubicweb_inlinedit/i18n/en.po
cubicweb_inlinedit/i18n/es.po
cubicweb_inlinedit/i18n/fr.po
cubicweb_inlinedit/migration/postcreate.py
cubicweb_inlinedit/views/__init__.py
cubicweb_inlinedit/views/controler.py
cubicweb_inlinedit/views/reledit.py
cubicweb_inlinedit-3.0.0.dist-info/METADATA
cubicweb_inlinedit-3.0.0.dist-info/WHEEL
cubicweb_inlinedit-3.0.0.dist-info/entry_points.txt
cubicweb_inlinedit-3.0.0.dist-info/top_level.txt
cubicweb_inlinedit-3.0.0.dist-info/RECORD
