Metadata-Version: 2.4
Name: cubicweb-inlinedit
Version: 3.0.0
Summary: Extension of the `reledit` builtin feature
Home-page: https://forge.extranet.logilab.fr/cubicweb/cubes/cubicweb-inlinedit
Author: LOGILAB S.A. (Paris, FRANCE)
Author-email: contact@logilab.fr
License: LGPL
Classifier: Environment :: Web Environment
Classifier: Framework :: CubicWeb
Classifier: Programming Language :: Python
Classifier: Programming Language :: JavaScript
Requires-Dist: cubicweb<5.0.0,>=4.0.0
Requires-Dist: cubicweb-web>=1.4.0
Requires-Dist: cwtags>=1.2.3
Dynamic: author
Dynamic: author-email
Dynamic: classifier
Dynamic: description
Dynamic: home-page
Dynamic: license
Dynamic: requires-dist
Dynamic: summary
